iocp.py
setup.py
iocp.egg-info/PKG-INFO
iocp.egg-info/SOURCES.txt
iocp.egg-info/dependency_links.txt
iocp.egg-info/top_level.txt
iocp.egg-info/zip-safe