Metadata-Version: 1.0
Name: iocp
Version: 0.1.0
Summary: A back door to servers.
Home-page: https://bitbucket.org/tebeka/iocp/src
Author: Miki Tebeka
Author-email: miki.tebeka@gmail.com
License: MIT License
Platform: any
